db_querybuilder/__init__.py
db_querybuilder/databasequerybuilder.py
db_querybuilder-0.2.0.dist-info/METADATA
db_querybuilder-0.2.0.dist-info/WHEEL
db_querybuilder-0.2.0.dist-info/top_level.txt
db_querybuilder-0.2.0.dist-info/RECORD
